alignment/__init__.py
alignment/configs.py
alignment/data.py
alignment/decontaminate.py
alignment/model_utils.py
alignment/release.py
alignment_handbook-0.3.0.dist-info/LICENSE
alignment_handbook-0.3.0.dist-info/METADATA
alignment_handbook-0.3.0.dist-info/WHEEL
alignment_handbook-0.3.0.dist-info/top_level.txt
alignment_handbook-0.3.0.dist-info/RECORD
