Metadata-Version: 2.1
Name: alignment-handbook
Version: 0.3.0
Summary: The Alignment Handbook
Home-page: https://github.com/huggingface/alignment-handbook
Author: The Hugging Face team (past and future)
Author-email: lewis@huggingface.co
License: Apache
Keywords: nlp deep learning rlhf llm
Platform: UNKNOWN
Classifier: Development Status :: 3 - Alpha
Classifier: Intended Audience :: Developers
Classifier: Intended Audience :: Education
Classifier: Intended Audience :: Science/Research
Classifier: License :: OSI Approved :: Apache Software License
Classifier: Operating System :: OS Independent
Classifier: Programming Language :: Python :: 3
Classifier: Programming Language :: Python :: 3.10
Classifier: Topic :: Scientific/Engineering :: Artificial Intelligence
Requires-Python: >=3.10.9
License-File: LICENSE
Requires-Dist: accelerate (>=0.29.2)
Requires-Dist: bitsandbytes (>=0.43.0)
Requires-Dist: einops (>=0.6.1)
Requires-Dist: evaluate (==0.4.0)
Requires-Dist: datasets (>=2.18.0)
Requires-Dist: deepspeed (>=0.14.4)
Requires-Dist: hf-transfer (>=0.1.4)
Requires-Dist: huggingface-hub (<1.0,>=0.19.2)
Requires-Dist: jinja2 (>=3.0.0)
Requires-Dist: ninja (>=1.11.1)
Requires-Dist: numpy (>=1.24.2)
Requires-Dist: packaging (>=23.0)
Requires-Dist: peft (>=0.9.0)
Requires-Dist: protobuf (<=3.20.2)
Requires-Dist: safetensors (>=0.3.3)
Requires-Dist: sentencepiece (>=0.1.99)
Requires-Dist: scipy
Requires-Dist: tensorboard
Requires-Dist: tqdm (>=4.64.1)
Requires-Dist: transformers (>=4.39.3)
Requires-Dist: trl (>=0.9.6)
Provides-Extra: dev
Requires-Dist: hf-doc-builder (>=0.4.0) ; extra == 'dev'
Requires-Dist: black (>=24.4.2) ; extra == 'dev'
Requires-Dist: isort (>=5.12.0) ; extra == 'dev'
Requires-Dist: flake8 (>=6.0.0) ; extra == 'dev'
Requires-Dist: pytest ; extra == 'dev'
Requires-Dist: parameterized (>=0.9.0) ; extra == 'dev'
Provides-Extra: docs
Requires-Dist: hf-doc-builder (>=0.4.0) ; extra == 'docs'
Provides-Extra: quality
Requires-Dist: black (>=24.4.2) ; extra == 'quality'
Requires-Dist: isort (>=5.12.0) ; extra == 'quality'
Requires-Dist: flake8 (>=6.0.0) ; extra == 'quality'
Provides-Extra: tests
Requires-Dist: pytest ; extra == 'tests'
Requires-Dist: parameterized (>=0.9.0) ; extra == 'tests'
Provides-Extra: torch
Requires-Dist: torch (>=2.1.2) ; extra == 'torch'
